{"saveDate":"2024-04-21","saveTime":"05:19:27","time":0.0,"day":0,"dropActive":[true,true,true,true,true,true,true,true,true,true,true,true,true,true,true,true,true,true,true,true,true,true,true,true,true,true,true,true,true,true,true,true,true,true,true,true,true,true],"palDatas":[{"key":0,"id":2,"lv":1},{"key":1,"id":1,"lv":1}],"playerData":{"lv":1,"exp":10,"hungry":100.0,"health":500.0,"maxHealth":500.0,"moveWeight":300.0,"skillPoint":3,"TechPoint":10,"maxStamina":100.0,"nowStamina":100.004318,"playerPosX":-10.6827288,"playerPosY":-1.10731661},"itemDatas":[{"key":0,"id":1,"count":8},{"key":1,"id":2,"count":8},{"key":2,"id":3,"count":1}],"itemSum":{"1":8,"2":8,"3":1},"techList":[],"furnitureDatas":[]}